libyear/__init__.py
libyear/pypi.py
libyear/utils.py
libyear-0.2.1.data/scripts/libyear
libyear-0.2.1.dist-info/METADATA
libyear-0.2.1.dist-info/WHEEL
libyear-0.2.1.dist-info/top_level.txt
libyear-0.2.1.dist-info/RECORD
