Metadata-Version: 2.1
Name: libyear
Version: 0.2.1
Summary: A simple measure of software dependency freshness.
Home-page: https://github.com/nasirhjafri/libyear
Author: nasirhjafri
License: UNKNOWN
Platform: UNKNOWN
Classifier: Development Status :: 5 - Production/Stable
Classifier: Environment :: Console
Classifier: Environment :: Other Environment
Classifier: Intended Audience :: Developers
Classifier: Operating System :: OS Independent
Classifier: Programming Language :: Python
Classifier: License :: OSI Approved :: MIT License
Requires-Dist: requests (>=2.0.0)
Requires-Dist: prettytable (>=0.7.2)
Requires-Dist: python-dateutil (>=2.7.0)
